pyjami/__init__.py
pyjami/java_symbol_migration_helpers.py
pyjami/sort_components_in_contract.py
pyjami-0.1.6.dist-info/METADATA
pyjami-0.1.6.dist-info/LICENSE
pyjami-0.1.6.dist-info/WHEEL
pyjami-0.1.6.dist-info/RECORD
