Metadata-Version: 2.1
Name: pyjami
Version: 0.1.6
Summary: Migrate Java code with Python.
Author: Mingyang Li
Author-email: mingyli@ebay.com
Requires-Python: >=3.10,<4.0
Classifier: Programming Language :: Python :: 3
Classifier: Programming Language :: Python :: 3.10
Classifier: Programming Language :: Python :: 3.11
Requires-Dist: PyYAML (>=6.0,<7.0)
Requires-Dist: docopt (>=0.6.2,<0.7.0)
Requires-Dist: pandas (>=1.5.0,<2.0.0)
